session_log_scrapping.py
session_log_scrapping-1.0.dist-info/licenses/LICENSE.txt
session_log_scrapping-1.0.dist-info/METADATA
session_log_scrapping-1.0.dist-info/WHEEL
session_log_scrapping-1.0.dist-info/top_level.txt
session_log_scrapping-1.0.dist-info/RECORD
