Metadata-Version: 2.4
Name: session_log_scrapping
Version: 1.0
Summary: This is to get the summarized details of the IICS session log
Author-email: Sai Prakash Simhadri <saiprakashsimhadri@gmail.com>
License: MIT
Project-URL: Homepage, https://github.com/saiprakashsimhadri/session_log_scrapping
Requires-Python: >=3.8
License-File: LICENSE.txt
Dynamic: license-file
